seqreads/__init__.py
seqreads-0.1.2.dist-info/LICENSE.txt
seqreads-0.1.2.dist-info/METADATA
seqreads-0.1.2.dist-info/WHEEL
seqreads-0.1.2.dist-info/top_level.txt
seqreads-0.1.2.dist-info/RECORD
