Metadata-Version: 2.1
Name: seqreads
Version: 0.1.2
Summary: seqreads
Author-email: Johannes <johannes-programming@mailfence.com>, Johannes <johannes-programming@posteo.net>
License: The MIT License (MIT)
Project-URL: Documentation, https://pypi.org/project/seqreads
Project-URL: Download, https://pypi.org/project/seqreads/#files
Project-URL: Source, https://github.com/johannes-programming/seqreads
Classifier: License :: OSI Approved :: MIT License
Classifier: Programming Language :: Python
Classifier: Programming Language :: Python :: 3
Classifier: Programming Language :: Python :: 3 :: Only
Requires-Python: >=3.11
License-File: LICENSE.txt
Requires-Dist: Bio >=1.6
Requires-Dist: na-quantors >=1.0
